chrhyme/__init__.py
chrhyme/__main__.py
chrhyme/data_prep.py
chrhyme/parser.py
chrhyme/phrase_dict.py
chrhyme/ryhthm_generator.py
chrhyme-0.1.3.dist-info/DESCRIPTION.rst
chrhyme-0.1.3.dist-info/METADATA
chrhyme-0.1.3.dist-info/RECORD
chrhyme-0.1.3.dist-info/WHEEL
chrhyme-0.1.3.dist-info/entry_points.txt
chrhyme-0.1.3.dist-info/metadata.json
chrhyme-0.1.3.dist-info/top_level.txt
