Metadata-Version: 2.0
Name: chrhyme
Version: 0.1.3
Summary: Cleaned code a little bit.
Home-page: https://github.com/jiaeyan/Chinese-Rhyme
Author: Jiajie Yan
Author-email: jiaeyan@gmail.com
License: MIT
Keywords: chinese,rhymes,rhythm,rap,rapper,hip-pop,poem
Platform: UNKNOWN
Classifier: Intended Audience :: Developers
Classifier: Operating System :: OS Independent
Classifier: Programming Language :: Python :: 3
Requires-Python: >=3
Requires-Dist: pypinyin
